oxdls.py
omexml_dls-1.1.0.dist-info/LICENSE
omexml_dls-1.1.0.dist-info/METADATA
omexml_dls-1.1.0.dist-info/WHEEL
omexml_dls-1.1.0.dist-info/top_level.txt
omexml_dls-1.1.0.dist-info/RECORD
