Metadata-Version: 2.1
Name: omexml-dls
Version: 1.1.0
Summary: Package for simple and consistent creation and parsing of OME metadata for B24 of Diamond Light Source Ltd.
Home-page: https://github.com/DiamondLightSource/python-omexml-dls
Author: Thomas M Fish
Author-email: thomas.fish@diamond.ac.uk
License: UNKNOWN
Platform: UNKNOWN
Classifier: Programming Language :: Python :: 2.7
Classifier: Programming Language :: Python :: 3
Classifier: License :: OSI Approved :: BSD License
Classifier: Operating System :: OS Independent
Classifier: Topic :: Scientific/Engineering :: Bio-Informatics
Requires-Python: >=2.7
License-File: LICENSE
Requires-Dist: future
Provides-Extra: test
Requires-Dist: pytest ; extra == 'test'
